boa_solidity/Counter.sol
boa_solidity/__init__.py
boa_solidity/soldeployer.py
boa_solidity-0.1.1.dist-info/METADATA
boa_solidity-0.1.1.dist-info/WHEEL
boa_solidity-0.1.1.dist-info/RECORD
